scale_core/__init__.py
scale_core/core/__init__.py
scale_core/core/futures.py
scale_core/core/scale.py
scale_core/core/scaling.py
scale_core/core/utils.py
scale_core/core/workers.py
scale_core/fast_api.py
scale_core/test4.py
scale_core/test5.py
scale_core-0.1.0.dist-info/METADATA
scale_core-0.1.0.dist-info/WHEEL
scale_core-0.1.0.dist-info/RECORD
